{
  "generated_at": "2026-01-26T02:34:51Z",
  "layers": [
    {
      "layer_id": 1,
      "generated_at": "2026-01-26T02:34:51Z",
      "connections": [
        {
          "pair": "C-5-C-8",
          "resonance": 0.338192,
          "layer": 1
        },
        {
          "pair": "C-1-C-4",
          "resonance": 0.154529,
          "layer": 1
        },
        {
          "pair": "C-4-C-8",
          "resonance": 0.159265,
          "layer": 1
        },
        {
          "pair": "C-3-C-5",
          "resonance": 0.622039,
          "layer": 1
        },
        {
          "pair": "C-7-C-8",
          "resonance": 0.209195,
          "layer": 1
        },
        {
          "pair": "C-1-C-7",
          "resonance": 0.187658,
          "layer": 1
        },
        {
          "pair": "C-2-C-6",
          "resonance": 0.469502,
          "layer": 1
        },
        {
          "pair": "C-1-C-6",
          "resonance": 0.583677,
          "layer": 1
        },
        {
          "pair": "C-1-C-2",
          "resonance": 0.232343,
          "layer": 1
        }
      ]
    },
    {
      "layer_id": 2,
      "generated_at": "2026-01-26T02:34:51Z",
      "connections": [
        {
          "pair": "C-6-C-7",
          "resonance": 0.363742,
          "layer": 2
        },
        {
          "pair": "C-1-C-8",
          "resonance": 0.26506,
          "layer": 2
        },
        {
          "pair": "C-2-C-3",
          "resonance": 0.660179,
          "layer": 2
        },
        {
          "pair": "C-3-C-6",
          "resonance": 0.889291,
          "layer": 2
        }
      ]
    },
    {
      "layer_id": 3,
      "generated_at": "2026-01-26T02:34:51Z",
      "connections": [
        {
          "pair": "C-5-C-8",
          "resonance": 0.323518,
          "layer": 3
        },
        {
          "pair": "C-2-C-6",
          "resonance": 0.58893,
          "layer": 3
        },
        {
          "pair": "C-5-C-6",
          "resonance": 0.528216,
          "layer": 3
        },
        {
          "pair": "C-1-C-2",
          "resonance": 0.258346,
          "layer": 3
        },
        {
          "pair": "C-3-C-5",
          "resonance": 0.543844,
          "layer": 3
        },
        {
          "pair": "C-1-C-4",
          "resonance": 0.182229,
          "layer": 3
        },
        {
          "pair": "C-7-C-8",
          "resonance": 0.226122,
          "layer": 3
        },
        {
          "pair": "C-6-C-8",
          "resonance": 0.558589,
          "layer": 3
        },
        {
          "pair": "C-1-C-7",
          "resonance": 0.179564,
          "layer": 3
        }
      ]
    }
  ]
}