{
  "generated_at": "2025-12-12T22:38:06Z",
  "engine": "Dynamic C-Engine",
  "cluster_count": 8,
  "clusters": [
    {
      "id": 1,
      "label": "C-1",
      "weight": 0.36537,
      "entropy": 0.65012,
      "timestamp": "2025-12-12T22:38:06Z"
    },
    {
      "id": 2,
      "label": "C-2",
      "weight": 0.18144,
      "entropy": 0.59776,
      "timestamp": "2025-12-12T22:38:06Z"
    },
    {
      "id": 3,
      "label": "C-3",
      "weight": 0.35713,
      "entropy": 0.75333,
      "timestamp": "2025-12-12T22:38:06Z"
    },
    {
      "id": 4,
      "label": "C-4",
      "weight": 0.9264,
      "entropy": 0.68534,
      "timestamp": "2025-12-12T22:38:06Z"
    },
    {
      "id": 5,
      "label": "C-5",
      "weight": 0.50266,
      "entropy": 0.902,
      "timestamp": "2025-12-12T22:38:06Z"
    },
    {
      "id": 6,
      "label": "C-6",
      "weight": 0.95252,
      "entropy": 0.51454,
      "timestamp": "2025-12-12T22:38:06Z"
    },
    {
      "id": 7,
      "label": "C-7",
      "weight": 0.97797,
      "entropy": 0.85767,
      "timestamp": "2025-12-12T22:38:06Z"
    },
    {
      "id": 8,
      "label": "C-8",
      "weight": 0.15414,
      "entropy": 0.56903,
      "timestamp": "2025-12-12T22:38:06Z"
    }
  ]
}